SFrame-2.1.dist-info/DESCRIPTION.rst
SFrame-2.1.dist-info/METADATA
SFrame-2.1.dist-info/RECORD
SFrame-2.1.dist-info/WHEEL
SFrame-2.1.dist-info/metadata.json
SFrame-2.1.dist-info/top_level.txt
sframe/__init__.py
sframe/_gl_pickle.py
sframe/_json.py
sframe/_minipsutil.py
sframe/aggregate.py
sframe/dependencies.py
sframe/extensions.py
sframe/generic.py
sframe/libadditional_sframe_utilities.dll
sframe/libeay32.dll
sframe/libgrouped_sframe.dll
sframe/libhdfs.so
sframe/libiconv-2.dll
sframe/libinternal_demo.dll
sframe/libjson.dll
sframe/libminipsutil.dll
sframe/librandom_sframe_generation.dll
sframe/libssh2-1.dll
sframe/libunity_core_shared.dll
sframe/libunity_server.dll
sframe/libunity_toolkits_shared.dll
sframe/libwinpthread-1.dll
sframe/sys_util.py
sframe/version_info.py
sframe/zlib1.dll
sframe/_scripts/__init__.py
sframe/_scripts/_pylambda_worker.py
sframe/connect/__init__.py
sframe/connect/main.py
sframe/cython/__init__.py
sframe/cython/context.py
sframe/cython/cy_callback.pyd
sframe/cython/cy_cpp_utils.pyd
sframe/cython/cy_dataframe.pyd
sframe/cython/cy_flexible_type.pyd
sframe/cython/cy_graph.pyd
sframe/cython/cy_ipc.pyd
sframe/cython/cy_model.pyd
sframe/cython/cy_pylambda_workers.pyd
sframe/cython/cy_sarray.pyd
sframe/cython/cy_sarray_builder.pyd
sframe/cython/cy_server.pyd
sframe/cython/cy_sframe.pyd
sframe/cython/cy_sframe_builder.pyd
sframe/cython/cy_sketch.pyd
sframe/cython/cy_test_utils.pyd
sframe/cython/cy_unity.pyd
sframe/cython/cy_variant.pyd
sframe/cython/libeay32.dll
sframe/cython/libhdfs.so
sframe/cython/libiconv-2.dll
sframe/cython/libminipsutil.dll
sframe/cython/libssh2-1.dll
sframe/cython/libunity_core_shared.dll
sframe/cython/libunity_server.dll
sframe/cython/libunity_toolkits_shared.dll
sframe/cython/libwinpthread-1.dll
sframe/cython/python_printer_callback.py
sframe/cython/zlib1.dll
sframe/data_structures/DBConnection.py
sframe/data_structures/__init__.py
sframe/data_structures/gframe.py
sframe/data_structures/grouped_sframe.py
sframe/data_structures/image.py
sframe/data_structures/sarray.py
sframe/data_structures/sarray_builder.py
sframe/data_structures/sframe.py
